rsxml/__init__.py
rsxml/__version__.py
rsxml/constants.py
rsxml/dotenv.py
rsxml/etag.py
rsxml/py.typed
rsxml/rspaths.py
rsxml/util.py
rsxml/validation.py
rsxml/xml.py
rsxml/debug/__init__.py
rsxml/debug/debug_proc.py
rsxml/debug/loop_timer.py
rsxml/debug/timer.py
rsxml/debug/timer_buckets.py
rsxml/logging/__init__.py
rsxml/logging/logger.py
rsxml/logging/progress_bar.py
rsxml/project_xml/Analysis.py
rsxml/project_xml/Dataset.py
rsxml/project_xml/Geopackage.py
rsxml/project_xml/MetaData.py
rsxml/project_xml/Project.py
rsxml/project_xml/ProjectBounds.py
rsxml/project_xml/ProjectValidation.py
rsxml/project_xml/QAQCEvent.py
rsxml/project_xml/RSObj.py
rsxml/project_xml/Realization.py
rsxml/project_xml/Warehouse.py
rsxml/project_xml/__init__.py
rsxml/project_xml/common.py
rsxml-2.2.1.dist-info/licenses/LICENSE
rsxml-2.2.1.dist-info/METADATA
rsxml-2.2.1.dist-info/WHEEL
rsxml-2.2.1.dist-info/top_level.txt
rsxml-2.2.1.dist-info/RECORD
