Metadata-Version: 2.4
Name: rsxml
Version: 2.2.1
Summary: Riverscapes XML helpers for use across Python3 open-source GIS Stack
Author-email: Matt Reimer <info@northarrowresearch.com>
License: MIT
Project-URL: Source, https://github.com/Riverscapes/RiverscapesXML
Project-URL: Homepage, https://github.com/Riverscapes/RiverscapesXML
Project-URL: Issues, https://github.com/Riverscapes/RiverscapesXML/issues
Keywords: riverscapes,xml,gis,hydrology
Classifier: Development Status :: 4 - Beta
Classifier: Intended Audience :: Developers
Classifier: Topic :: Scientific/Engineering :: GIS
Classifier: Programming Language :: Python :: 3
Classifier: Programming Language :: Python :: 3.10
Classifier: Programming Language :: Python :: 3.11
Classifier: Programming Language :: Python :: 3.12
Classifier: Typing :: Typed
Classifier: Operating System :: OS Independent
Requires-Python: >=3.9
License-File: LICENSE
Requires-Dist: lxml>=4.9.2
Requires-Dist: requests>=2.31.0
Requires-Dist: semver>=2.10.2
Provides-Extra: dev
Requires-Dist: boto3>=1.42.10; extra == "dev"
Requires-Dist: botocore>=1.42.10; extra == "dev"
Requires-Dist: questionary>=2.1.1; extra == "dev"
Requires-Dist: pytest>=8.3.4; extra == "dev"
Requires-Dist: ruff>=0.1.0; extra == "dev"
Requires-Dist: nox>=2023.4.22; extra == "dev"
Requires-Dist: pre-commit>=3.5.0; extra == "dev"
Requires-Dist: termcolor>=2.3.0; extra == "dev"
Requires-Dist: jsonschema>=4.15.0; extra == "dev"
Dynamic: license-file
